<?xml version="1.0" encoding="UTF-8"?>
<?xml-stylesheet type="text/xsl" href="ipums-ddi-xslt.xsl"?>
<codeBook ID="ddi2-7ac4bf80-9b41-013b-2194-0242c0a83007-usa_00002.dat-usa.ipums.org" version="2.5" xmlns="ddi:codebook:2_5" xmlns:xsi="http://www.w3.org/2001/XMLSchema-instance" xsi:schemaLocation="ddi:codebook:2_5 http://www.ddialliance.org/Specification/DDI-Codebook/2.5/XMLSchema/codebook.xsd">
  <docDscr>
    <citation>
      <titlStmt>
        <titl>Codebook for an IPUMS-USA Data Extract</titl>
        <subTitl>DDI 2.5 metadata describing the extract file  'usa_00002.dat'</subTitl>
        <IDNo>ddi2-7ac4bf80-9b41-013b-2194-0242c0a83007-usa_00002.dat-usa.ipums.org</IDNo>
      </titlStmt>
      <rspStmt>
        <AuthEnty affiliation="University of Minnesota">IPUMS</AuthEnty>
      </rspStmt>
      <prodStmt>
        <producer abbr="IPUMS" affiliation="University of Minnesota" role="Documentation">IPUMS</producer>
        <prodDate date="2023-03-02">March 2, 2023</prodDate>
        <prodPlac>IPUMS, 50 Willey Hall, 225 - 19th Avenue South, Minneapolis, MN 55455</prodPlac>
      </prodStmt>
      <distStmt>
        <contact URI="https://ipums.org" affiliation="University of Minnesota">IPUMS</contact>
      </distStmt>
    </citation>
  </docDscr>
  <stdyDscr>
    <citation>
      <titlStmt>
        <titl>User Extract usa_00002.dat</titl>
      </titlStmt>
      <rspStmt>
        <AuthEnty affiliation="University of Minnesota">IPUMS</AuthEnty>
      </rspStmt>
      <prodStmt>
        <producer abbr="IPUMS" affiliation="University of Minnesota" role="Documentation">IPUMS</producer>
        <prodDate date="2023-03-02">March 2, 2023</prodDate>
        <prodPlac>IPUMS, 50 Willey Hall, 225 - 19th Avenue South, Minneapolis, MN 55455</prodPlac>
      </prodStmt>
      <distStmt>
        <contact URI="https://ipums.org" affiliation="University of Minnesota">IPUMS</contact>
      </distStmt>
      <serStmt>
        <serName abbr="usa">IPUMS USA</serName>
        <serInfo>DOI:10.18128/D010.V12.0</serInfo>
      </serStmt>
      <verStmt>
        <version date="2023-03-02"/>
      </verStmt>
    </citation>
    <stdyInfo>
      <subject>
        <topcClas vocab="IPUMS">Geographic Variables -- HOUSEHOLD</topcClas>
        <topcClas vocab="IPUMS">Technical Variables -- PERSON</topcClas>
        <topcClas vocab="IPUMS">Demographic Variables -- PERSON</topcClas>
        <topcClas vocab="IPUMS">Race, Ethnicity, and Nativity Variables -- PERSON</topcClas>
        <topcClas vocab="IPUMS">Work Variables -- PERSON</topcClas>
        <topcClas vocab="IPUMS">Income Variables -- PERSON</topcClas>
      </subject>
      <sumDscr ID="sdatref-2717">
        <timePrd date="2021" event="single">2021</timePrd>
        <nation abbr="us">United States</nation>
      </sumDscr>
      <notes><![CDATA[Additional notes on a sample that is part of this study:  2021 ACS
            Density of the full data file:  1.0%
            Density of this extract: 1.0%
]]></notes>
    </stdyInfo>
    <dataAccs>
      <useStmt>
        <confDec required="no"><![CDATA[None]]></confDec>
        <contact URI="http://usa.ipums.org" affiliation="IPUMS">IPUMS-USA</contact>
        <citReq><![CDATA[Publications and research reports based on the IPUMS-USA database must cite it appropriately. The citation should include the following:

Steven Ruggles, Sarah Flood, Ronald Goeken, Megan Schouweiler and Matthew Sobek. IPUMS USA: Version 12.0 [dataset]. Minneapolis, MN: IPUMS, 2022. https://doi.org/10.18128/D010.V12.0

The licensing agreement for use of IPUMS-USA data requires that users supply us with the title and full citation for any publications, research reports, or educational materials making use of the data or documentation. Please add your citation to the IPUMS bibliography at http://bibliography.ipums.org/.]]></citReq>
        <conditions><![CDATA[Users of IPUMS-USA data must agree to abide by the conditions of use. A user's license is valid for one year and may be renewed.  Users must agree to the following conditions:

(1) No fees may be charged for use or distribution of the data.

(2) Cite IPUMS appropriately.  For information on proper citation,  refer to the citation requirement section of this DDI document.

(3) Tell us about any work you do using the IPUMS.  Publications, research  reports, or presentations making use of IPUMS-USA should be added to our  Bibliography. Continued funding for the IPUMS depends on our ability to  show our sponsor agencies that researchers are using the data for productive  purposes.

(4) The IPUMS cannot be used for genealogical research

(5) It is difficult to use the IPUMS to study small geographic areas.  In the  IPUMS census samples for years 1940-present, no places having a population  of fewer than 100,000 persons can be identified.

(6) Use it for GOOD -- never for EVIL.

(7) Please notify ipums@umn.edu regarding errors in the data or documentation.]]></conditions>
        <disclaimer>The user of the data acknowledges that the original collector of the data, the authorized distributor of the data, and the relevant funding agency bear no responsibility for use of the data or for interpretations or inferences based upon such uses.</disclaimer>
      </useStmt>
    </dataAccs>
    <notes><![CDATA[User-provided description:  simple_sex_age_state_race]]></notes>
    <notes>This extract is a revision of the user's previous extract, ID 17820174.</notes>
  </stdyDscr>
  <fileDscr ID="ExtractData">
    <fileTxt>
      <fileName>usa_00002.dat</fileName>
      <fileCont>Microdata records</fileCont>
      <fileStrc type="rectangular"/>
      <fileType charset="ISO-8859-1">ISO-8859-1 data file</fileType>
      <format>fixed length fields</format>
      <filePlac>IPUMS, 50 Willey Hall, 225 - 19th Avenue South, Minneapolis, MN 55455</filePlac>
    </fileTxt>
  </fileDscr>
  <dataDscr>
    <var ID="STATEFIP" dcml="0" files="ExtractData" intrvl="discrete" name="STATEFIP">
      <location EndPos="2" StartPos="1" width="2"/>
      <labl>State (FIPS code)</labl>
      <txt><![CDATA[STATEFIP reports the state in which the household was located, using the Federal Information Processing Standards (FIPS) coding scheme, which orders the states alphabetically.

In the 1980 Urban/Rural sample, STATEFIP identifies state groups that are not available in STATEICP; these state groups (codes 61-68) are only available for that particular sample. 

See "Geographic Coding and Comparability" for more information on the geographic detail available in particular samples.]]></txt>
      <catgry>
        <catValu>01</catValu>
        <labl>Alabama</labl>
      </catgry>
      <catgry>
        <catValu>02</catValu>
        <labl>Alaska</labl>
      </catgry>
      <catgry>
        <catValu>04</catValu>
        <labl>Arizona</labl>
      </catgry>
      <catgry>
        <catValu>05</catValu>
        <labl>Arkansas</labl>
      </catgry>
      <catgry>
        <catValu>06</catValu>
        <labl>California</labl>
      </catgry>
      <catgry>
        <catValu>08</catValu>
        <labl>Colorado</labl>
      </catgry>
      <catgry>
        <catValu>09</catValu>
        <labl>Connecticut</labl>
      </catgry>
      <catgry>
        <catValu>10</catValu>
        <labl>Delaware</labl>
      </catgry>
      <catgry>
        <catValu>11</catValu>
        <labl>District of Columbia</labl>
      </catgry>
      <catgry>
        <catValu>12</catValu>
        <labl>Florida</labl>
      </catgry>
      <catgry>
        <catValu>13</catValu>
        <labl>Georgia</labl>
      </catgry>
      <catgry>
        <catValu>15</catValu>
        <labl>Hawaii</labl>
      </catgry>
      <catgry>
        <catValu>16</catValu>
        <labl>Idaho</labl>
      </catgry>
      <catgry>
        <catValu>17</catValu>
        <labl>Illinois</labl>
      </catgry>
      <catgry>
        <catValu>18</catValu>
        <labl>Indiana</labl>
      </catgry>
      <catgry>
        <catValu>19</catValu>
        <labl>Iowa</labl>
      </catgry>
      <catgry>
        <catValu>20</catValu>
        <labl>Kansas</labl>
      </catgry>
      <catgry>
        <catValu>21</catValu>
        <labl>Kentucky</labl>
      </catgry>
      <catgry>
        <catValu>22</catValu>
        <labl>Louisiana</labl>
      </catgry>
      <catgry>
        <catValu>23</catValu>
        <labl>Maine</labl>
      </catgry>
      <catgry>
        <catValu>24</catValu>
        <labl>Maryland</labl>
      </catgry>
      <catgry>
        <catValu>25</catValu>
        <labl>Massachusetts</labl>
      </catgry>
      <catgry>
        <catValu>26</catValu>
        <labl>Michigan</labl>
      </catgry>
      <catgry>
        <catValu>27</catValu>
        <labl>Minnesota</labl>
      </catgry>
      <catgry>
        <catValu>28</catValu>
        <labl>Mississippi</labl>
      </catgry>
      <catgry>
        <catValu>29</catValu>
        <labl>Missouri</labl>
      </catgry>
      <catgry>
        <catValu>30</catValu>
        <labl>Montana</labl>
      </catgry>
      <catgry>
        <catValu>31</catValu>
        <labl>Nebraska</labl>
      </catgry>
      <catgry>
        <catValu>32</catValu>
        <labl>Nevada</labl>
      </catgry>
      <catgry>
        <catValu>33</catValu>
        <labl>New Hampshire</labl>
      </catgry>
      <catgry>
        <catValu>34</catValu>
        <labl>New Jersey</labl>
      </catgry>
      <catgry>
        <catValu>35</catValu>
        <labl>New Mexico</labl>
      </catgry>
      <catgry>
        <catValu>36</catValu>
        <labl>New York</labl>
      </catgry>
      <catgry>
        <catValu>37</catValu>
        <labl>North Carolina</labl>
      </catgry>
      <catgry>
        <catValu>38</catValu>
        <labl>North Dakota</labl>
      </catgry>
      <catgry>
        <catValu>39</catValu>
        <labl>Ohio</labl>
      </catgry>
      <catgry>
        <catValu>40</catValu>
        <labl>Oklahoma</labl>
      </catgry>
      <catgry>
        <catValu>41</catValu>
        <labl>Oregon</labl>
      </catgry>
      <catgry>
        <catValu>42</catValu>
        <labl>Pennsylvania</labl>
      </catgry>
      <catgry>
        <catValu>44</catValu>
        <labl>Rhode Island</labl>
      </catgry>
      <catgry>
        <catValu>45</catValu>
        <labl>South Carolina</labl>
      </catgry>
      <catgry>
        <catValu>46</catValu>
        <labl>South Dakota</labl>
      </catgry>
      <catgry>
        <catValu>47</catValu>
        <labl>Tennessee</labl>
      </catgry>
      <catgry>
        <catValu>48</catValu>
        <labl>Texas</labl>
      </catgry>
      <catgry>
        <catValu>49</catValu>
        <labl>Utah</labl>
      </catgry>
      <catgry>
        <catValu>50</catValu>
        <labl>Vermont</labl>
      </catgry>
      <catgry>
        <catValu>51</catValu>
        <labl>Virginia</labl>
      </catgry>
      <catgry>
        <catValu>53</catValu>
        <labl>Washington</labl>
      </catgry>
      <catgry>
        <catValu>54</catValu>
        <labl>West Virginia</labl>
      </catgry>
      <catgry>
        <catValu>55</catValu>
        <labl>Wisconsin</labl>
      </catgry>
      <catgry>
        <catValu>56</catValu>
        <labl>Wyoming</labl>
      </catgry>
      <catgry>
        <catValu>61</catValu>
        <labl>Maine-New Hampshire-Vermont</labl>
      </catgry>
      <catgry>
        <catValu>62</catValu>
        <labl>Massachusetts-Rhode Island</labl>
      </catgry>
      <catgry>
        <catValu>63</catValu>
        <labl>Minnesota-Iowa-Missouri-Kansas-Nebraska-S.Dakota-N.Dakota</labl>
      </catgry>
      <catgry>
        <catValu>64</catValu>
        <labl>Maryland-Delaware</labl>
      </catgry>
      <catgry>
        <catValu>65</catValu>
        <labl>Montana-Idaho-Wyoming</labl>
      </catgry>
      <catgry>
        <catValu>66</catValu>
        <labl>Utah-Nevada</labl>
      </catgry>
      <catgry>
        <catValu>67</catValu>
        <labl>Arizona-New Mexico</labl>
      </catgry>
      <catgry>
        <catValu>68</catValu>
        <labl>Alaska-Hawaii</labl>
      </catgry>
      <catgry>
        <catValu>72</catValu>
        <labl>Puerto Rico</labl>
      </catgry>
      <catgry>
        <catValu>97</catValu>
        <labl>Military/Mil. Reservation</labl>
      </catgry>
      <catgry>
        <catValu>99</catValu>
        <labl>State not identified</labl>
      </catgry>
      <concept vocab="IPUMS">Geographic Variables -- HOUSEHOLD</concept>
      <varFormat schema="other" type="numeric"/>
    </var>
    <var ID="PERWT" dcml="2" files="ExtractData" intrvl="contin" name="PERWT">
      <location EndPos="12" StartPos="3" width="10"/>
      <labl>Person weight</labl>
      <txt><![CDATA[PERWT indicates how many persons in the U.S. population are represented by a given person in an IPUMS sample. 

It is generally a good idea to use PERWT when conducting a person-level analysis of any IPUMS sample. The use of PERWT is optional when analyzing one of the "flat" or unweighted IPUMS samples. Flat IPUMS samples include the 1% samples from 1850-1930, all samples from 1960, 1970, and 1980, the 1% unweighted samples from 1990 and 2000, the 10% 2010 sample, and any of the full count 100% census datasets. PERWT must be used to obtain nationally representative statistics for person-level analyses of any sample other than those.

For further explanation of the sample weights, see "Sample Designs" and "Sample Weights". See also HHWT for a corresponding variable at the household level, and SLWT for a weight variable used with sample-line records in 1940 and 1950.]]></txt>
      <codInstr><![CDATA[CodesPERWT is a 6-digit numeric variable which indicates how many persons in the U.S. population are represented by a given person in an IPUMS sample and has two implied decimals. For example, a PERWT value of 010461 should be interpreted as 104.61. PERWT specific variable codes for missing, edited, or unidentified observations, observations not applicable (N/A), observations not in universe (NIU), top and bottom value coding, etc. are provided below if applicable by Census year (and data sample if specified).

PERWT Specific Variable Codes]]></codInstr>
      <concept vocab="IPUMS">Technical Variables -- PERSON</concept>
      <varFormat schema="other" type="numeric"/>
    </var>
    <var ID="SEX" dcml="0" files="ExtractData" intrvl="discrete" name="SEX">
      <location EndPos="13" StartPos="13" width="1"/>
      <labl>Sex</labl>
      <txt><![CDATA[SEX reports whether the person was male or female.]]></txt>
      <catgry>
        <catValu>1</catValu>
        <labl>Male</labl>
      </catgry>
      <catgry>
        <catValu>2</catValu>
        <labl>Female</labl>
      </catgry>
      <concept vocab="IPUMS">Demographic Variables -- PERSON</concept>
      <varFormat schema="other" type="numeric"/>
    </var>
    <var ID="AGE" dcml="0" files="ExtractData" intrvl="discrete" name="AGE">
      <location EndPos="16" StartPos="14" width="3"/>
      <labl>Age</labl>
      <txt><![CDATA[AGE reports the person's age in years as of the last birthday.

Please see the Comparability section regarding a known Universe issue with AGE and AGEORIG which effects EMPSTAT and LABFORCE for the 2004 ACS Sample.]]></txt>
      <catgry>
        <catValu>000</catValu>
        <labl>Less than 1 year old</labl>
      </catgry>
      <catgry>
        <catValu>001</catValu>
        <labl>1</labl>
      </catgry>
      <catgry>
        <catValu>002</catValu>
        <labl>2</labl>
      </catgry>
      <catgry>
        <catValu>003</catValu>
        <labl>3</labl>
      </catgry>
      <catgry>
        <catValu>004</catValu>
        <labl>4</labl>
      </catgry>
      <catgry>
        <catValu>005</catValu>
        <labl>5</labl>
      </catgry>
      <catgry>
        <catValu>006</catValu>
        <labl>6</labl>
      </catgry>
      <catgry>
        <catValu>007</catValu>
        <labl>7</labl>
      </catgry>
      <catgry>
        <catValu>008</catValu>
        <labl>8</labl>
      </catgry>
      <catgry>
        <catValu>009</catValu>
        <labl>9</labl>
      </catgry>
      <catgry>
        <catValu>010</catValu>
        <labl>10</labl>
      </catgry>
      <catgry>
        <catValu>011</catValu>
        <labl>11</labl>
      </catgry>
      <catgry>
        <catValu>012</catValu>
        <labl>12</labl>
      </catgry>
      <catgry>
        <catValu>013</catValu>
        <labl>13</labl>
      </catgry>
      <catgry>
        <catValu>014</catValu>
        <labl>14</labl>
      </catgry>
      <catgry>
        <catValu>015</catValu>
        <labl>15</labl>
      </catgry>
      <catgry>
        <catValu>016</catValu>
        <labl>16</labl>
      </catgry>
      <catgry>
        <catValu>017</catValu>
        <labl>17</labl>
      </catgry>
      <catgry>
        <catValu>018</catValu>
        <labl>18</labl>
      </catgry>
      <catgry>
        <catValu>019</catValu>
        <labl>19</labl>
      </catgry>
      <catgry>
        <catValu>020</catValu>
        <labl>20</labl>
      </catgry>
      <catgry>
        <catValu>021</catValu>
        <labl>21</labl>
      </catgry>
      <catgry>
        <catValu>022</catValu>
        <labl>22</labl>
      </catgry>
      <catgry>
        <catValu>023</catValu>
        <labl>23</labl>
      </catgry>
      <catgry>
        <catValu>024</catValu>
        <labl>24</labl>
      </catgry>
      <catgry>
        <catValu>025</catValu>
        <labl>25</labl>
      </catgry>
      <catgry>
        <catValu>026</catValu>
        <labl>26</labl>
      </catgry>
      <catgry>
        <catValu>027</catValu>
        <labl>27</labl>
      </catgry>
      <catgry>
        <catValu>028</catValu>
        <labl>28</labl>
      </catgry>
      <catgry>
        <catValu>029</catValu>
        <labl>29</labl>
      </catgry>
      <catgry>
        <catValu>030</catValu>
        <labl>30</labl>
      </catgry>
      <catgry>
        <catValu>031</catValu>
        <labl>31</labl>
      </catgry>
      <catgry>
        <catValu>032</catValu>
        <labl>32</labl>
      </catgry>
      <catgry>
        <catValu>033</catValu>
        <labl>33</labl>
      </catgry>
      <catgry>
        <catValu>034</catValu>
        <labl>34</labl>
      </catgry>
      <catgry>
        <catValu>035</catValu>
        <labl>35</labl>
      </catgry>
      <catgry>
        <catValu>036</catValu>
        <labl>36</labl>
      </catgry>
      <catgry>
        <catValu>037</catValu>
        <labl>37</labl>
      </catgry>
      <catgry>
        <catValu>038</catValu>
        <labl>38</labl>
      </catgry>
      <catgry>
        <catValu>039</catValu>
        <labl>39</labl>
      </catgry>
      <catgry>
        <catValu>040</catValu>
        <labl>40</labl>
      </catgry>
      <catgry>
        <catValu>041</catValu>
        <labl>41</labl>
      </catgry>
      <catgry>
        <catValu>042</catValu>
        <labl>42</labl>
      </catgry>
      <catgry>
        <catValu>043</catValu>
        <labl>43</labl>
      </catgry>
      <catgry>
        <catValu>044</catValu>
        <labl>44</labl>
      </catgry>
      <catgry>
        <catValu>045</catValu>
        <labl>45</labl>
      </catgry>
      <catgry>
        <catValu>046</catValu>
        <labl>46</labl>
      </catgry>
      <catgry>
        <catValu>047</catValu>
        <labl>47</labl>
      </catgry>
      <catgry>
        <catValu>048</catValu>
        <labl>48</labl>
      </catgry>
      <catgry>
        <catValu>049</catValu>
        <labl>49</labl>
      </catgry>
      <catgry>
        <catValu>050</catValu>
        <labl>50</labl>
      </catgry>
      <catgry>
        <catValu>051</catValu>
        <labl>51</labl>
      </catgry>
      <catgry>
        <catValu>052</catValu>
        <labl>52</labl>
      </catgry>
      <catgry>
        <catValu>053</catValu>
        <labl>53</labl>
      </catgry>
      <catgry>
        <catValu>054</catValu>
        <labl>54</labl>
      </catgry>
      <catgry>
        <catValu>055</catValu>
        <labl>55</labl>
      </catgry>
      <catgry>
        <catValu>056</catValu>
        <labl>56</labl>
      </catgry>
      <catgry>
        <catValu>057</catValu>
        <labl>57</labl>
      </catgry>
      <catgry>
        <catValu>058</catValu>
        <labl>58</labl>
      </catgry>
      <catgry>
        <catValu>059</catValu>
        <labl>59</labl>
      </catgry>
      <catgry>
        <catValu>060</catValu>
        <labl>60</labl>
      </catgry>
      <catgry>
        <catValu>061</catValu>
        <labl>61</labl>
      </catgry>
      <catgry>
        <catValu>062</catValu>
        <labl>62</labl>
      </catgry>
      <catgry>
        <catValu>063</catValu>
        <labl>63</labl>
      </catgry>
      <catgry>
        <catValu>064</catValu>
        <labl>64</labl>
      </catgry>
      <catgry>
        <catValu>065</catValu>
        <labl>65</labl>
      </catgry>
      <catgry>
        <catValu>066</catValu>
        <labl>66</labl>
      </catgry>
      <catgry>
        <catValu>067</catValu>
        <labl>67</labl>
      </catgry>
      <catgry>
        <catValu>068</catValu>
        <labl>68</labl>
      </catgry>
      <catgry>
        <catValu>069</catValu>
        <labl>69</labl>
      </catgry>
      <catgry>
        <catValu>070</catValu>
        <labl>70</labl>
      </catgry>
      <catgry>
        <catValu>071</catValu>
        <labl>71</labl>
      </catgry>
      <catgry>
        <catValu>072</catValu>
        <labl>72</labl>
      </catgry>
      <catgry>
        <catValu>073</catValu>
        <labl>73</labl>
      </catgry>
      <catgry>
        <catValu>074</catValu>
        <labl>74</labl>
      </catgry>
      <catgry>
        <catValu>075</catValu>
        <labl>75</labl>
      </catgry>
      <catgry>
        <catValu>076</catValu>
        <labl>76</labl>
      </catgry>
      <catgry>
        <catValu>077</catValu>
        <labl>77</labl>
      </catgry>
      <catgry>
        <catValu>078</catValu>
        <labl>78</labl>
      </catgry>
      <catgry>
        <catValu>079</catValu>
        <labl>79</labl>
      </catgry>
      <catgry>
        <catValu>080</catValu>
        <labl>80</labl>
      </catgry>
      <catgry>
        <catValu>081</catValu>
        <labl>81</labl>
      </catgry>
      <catgry>
        <catValu>082</catValu>
        <labl>82</labl>
      </catgry>
      <catgry>
        <catValu>083</catValu>
        <labl>83</labl>
      </catgry>
      <catgry>
        <catValu>084</catValu>
        <labl>84</labl>
      </catgry>
      <catgry>
        <catValu>085</catValu>
        <labl>85</labl>
      </catgry>
      <catgry>
        <catValu>086</catValu>
        <labl>86</labl>
      </catgry>
      <catgry>
        <catValu>087</catValu>
        <labl>87</labl>
      </catgry>
      <catgry>
        <catValu>088</catValu>
        <labl>88</labl>
      </catgry>
      <catgry>
        <catValu>089</catValu>
        <labl>89</labl>
      </catgry>
      <catgry>
        <catValu>090</catValu>
        <labl>90 (90+ in 1980 and 1990)</labl>
      </catgry>
      <catgry>
        <catValu>091</catValu>
        <labl>91</labl>
      </catgry>
      <catgry>
        <catValu>092</catValu>
        <labl>92</labl>
      </catgry>
      <catgry>
        <catValu>093</catValu>
        <labl>93</labl>
      </catgry>
      <catgry>
        <catValu>094</catValu>
        <labl>94</labl>
      </catgry>
      <catgry>
        <catValu>095</catValu>
        <labl>95</labl>
      </catgry>
      <catgry>
        <catValu>096</catValu>
        <labl>96</labl>
      </catgry>
      <catgry>
        <catValu>097</catValu>
        <labl>97</labl>
      </catgry>
      <catgry>
        <catValu>098</catValu>
        <labl>98</labl>
      </catgry>
      <catgry>
        <catValu>099</catValu>
        <labl>99</labl>
      </catgry>
      <catgry>
        <catValu>100</catValu>
        <labl>100 (100+ in 1960-1970)</labl>
      </catgry>
      <catgry>
        <catValu>101</catValu>
        <labl>101</labl>
      </catgry>
      <catgry>
        <catValu>102</catValu>
        <labl>102</labl>
      </catgry>
      <catgry>
        <catValu>103</catValu>
        <labl>103</labl>
      </catgry>
      <catgry>
        <catValu>104</catValu>
        <labl>104</labl>
      </catgry>
      <catgry>
        <catValu>105</catValu>
        <labl>105</labl>
      </catgry>
      <catgry>
        <catValu>106</catValu>
        <labl>106</labl>
      </catgry>
      <catgry>
        <catValu>107</catValu>
        <labl>107</labl>
      </catgry>
      <catgry>
        <catValu>108</catValu>
        <labl>108</labl>
      </catgry>
      <catgry>
        <catValu>109</catValu>
        <labl>109</labl>
      </catgry>
      <catgry>
        <catValu>110</catValu>
        <labl>110</labl>
      </catgry>
      <catgry>
        <catValu>111</catValu>
        <labl>111</labl>
      </catgry>
      <catgry>
        <catValu>112</catValu>
        <labl>112 (112+ in the 1980 internal data)</labl>
      </catgry>
      <catgry>
        <catValu>113</catValu>
        <labl>113</labl>
      </catgry>
      <catgry>
        <catValu>114</catValu>
        <labl>114</labl>
      </catgry>
      <catgry>
        <catValu>115</catValu>
        <labl>115 (115+ in the 1990 internal data)</labl>
      </catgry>
      <catgry>
        <catValu>116</catValu>
        <labl>116</labl>
      </catgry>
      <catgry>
        <catValu>117</catValu>
        <labl>117</labl>
      </catgry>
      <catgry>
        <catValu>118</catValu>
        <labl>118</labl>
      </catgry>
      <catgry>
        <catValu>119</catValu>
        <labl>119</labl>
      </catgry>
      <catgry>
        <catValu>120</catValu>
        <labl>120</labl>
      </catgry>
      <catgry>
        <catValu>121</catValu>
        <labl>121</labl>
      </catgry>
      <catgry>
        <catValu>122</catValu>
        <labl>122</labl>
      </catgry>
      <catgry>
        <catValu>123</catValu>
        <labl>123</labl>
      </catgry>
      <catgry>
        <catValu>124</catValu>
        <labl>124</labl>
      </catgry>
      <catgry>
        <catValu>125</catValu>
        <labl>125</labl>
      </catgry>
      <catgry>
        <catValu>126</catValu>
        <labl>126</labl>
      </catgry>
      <catgry>
        <catValu>129</catValu>
        <labl>129</labl>
      </catgry>
      <catgry>
        <catValu>130</catValu>
        <labl>130</labl>
      </catgry>
      <catgry>
        <catValu>135</catValu>
        <labl>135</labl>
      </catgry>
      <concept vocab="IPUMS">Demographic Variables -- PERSON</concept>
      <varFormat schema="other" type="numeric"/>
    </var>
    <var ID="RACE" dcml="0" files="ExtractData" intrvl="discrete" name="RACE">
      <location EndPos="17" StartPos="17" width="1"/>
      <labl>Race [general version]</labl>
      <txt><![CDATA[The concept of race has changed over the more than 150 years represented in IPUMS. Currently, the Census Bureau and others consider race to be a sociopolitical construct, not a scientific or anthropological one. Many detailed RACE categories consist of national origin groups. With the exception of the 1970-1990 Puerto Rican censuses, RACE was asked of every person in all years. 

Beginning in 2000, the race question changed substantially to allow respondents to report as many races as they felt necessary to describe themselves. In earlier years, only one race response was coded. Beginning in 2020, the Census Bureau updated the questionnaire text, processing, and coding of the race and Hispanic origin questions, resulting in major changes to the distribution of race and Hispanic origin categories. As a result, users should proceed with caution when comparing RACE and HISPAN in 2019-prior samples with 2020-onward samples. See the comparability tab for more details. 

IPUMS offers several variables describing the answer(s) to the race question. RACE provides the full detail given by the respondent and/or released by the Census Bureau; it is not always historically compatible (see comparability discussion below). Users primarily interested in historical compatibility should consider using RACHSING. RACHSING codes race and Hispanic origin responses into a simple, historically compatible scheme that includes only federally defined race and Hispanic origin groups. Please note that RACESING, an earlier version of RACHSING, is also available on the IPUMS website. 

In addition, specific combinations of major races can be discerned using the following bivariate indicators of whether a particular race group was reported: RACAMIND, RACASIAN, RACBLK, RACOTHER, RACPACIS, and RACWHT. RACNUM indicates the total number of major race groups reported for an individual. The information contained in the bivariate indicators and in RACNUM is integrated into the detailed version of RACE. 

Prior to 1960, the census enumerator was responsible for categorizing persons and was not specifically instructed to ask the individual his or her race. In 1970 and later years, an individual's race was reported by someone in the household or group quarters. In the 1990 U.S. census, the 2000 U.S. and Puerto Rican censuses, the ACS, and the PRCS respondents were specifically asked what race the person "considers himself/herself" to be, although such self-description was more or less operative since 1960.

User Note: Race questions were not asked in the Puerto Rican censuses of 1970, 1980, and 1990.  They were asked in the 1910 and 1920 Puerto Rican censuses, the 2000-2010 Puerto Rican censuses, and the PRCS.]]></txt>
      <catgry>
        <catValu>1</catValu>
        <labl>White</labl>
      </catgry>
      <catgry>
        <catValu>2</catValu>
        <labl>Black/African American</labl>
      </catgry>
      <catgry>
        <catValu>3</catValu>
        <labl>American Indian or Alaska Native</labl>
      </catgry>
      <catgry>
        <catValu>4</catValu>
        <labl>Chinese</labl>
      </catgry>
      <catgry>
        <catValu>5</catValu>
        <labl>Japanese</labl>
      </catgry>
      <catgry>
        <catValu>6</catValu>
        <labl>Other Asian or Pacific Islander</labl>
      </catgry>
      <catgry>
        <catValu>7</catValu>
        <labl>Other race, nec</labl>
      </catgry>
      <catgry>
        <catValu>8</catValu>
        <labl>Two major races</labl>
      </catgry>
      <catgry>
        <catValu>9</catValu>
        <labl>Three or more major races</labl>
      </catgry>
      <concept vocab="IPUMS">Race, Ethnicity, and Nativity Variables -- PERSON</concept>
      <varFormat schema="other" type="numeric"/>
    </var>
    <var ID="RACED" dcml="0" files="ExtractData" intrvl="discrete" name="RACED">
      <location EndPos="20" StartPos="18" width="3"/>
      <labl>Race [detailed version]</labl>
      <txt><![CDATA[The concept of race has changed over the more than 150 years represented in IPUMS. Currently, the Census Bureau and others consider race to be a sociopolitical construct, not a scientific or anthropological one. Many detailed RACE categories consist of national origin groups. With the exception of the 1970-1990 Puerto Rican censuses, RACE was asked of every person in all years. 

Beginning in 2000, the race question changed substantially to allow respondents to report as many races as they felt necessary to describe themselves. In earlier years, only one race response was coded. Beginning in 2020, the Census Bureau updated the questionnaire text, processing, and coding of the race and Hispanic origin questions, resulting in major changes to the distribution of race and Hispanic origin categories. As a result, users should proceed with caution when comparing RACE and HISPAN in 2019-prior samples with 2020-onward samples. See the comparability tab for more details. 

IPUMS offers several variables describing the answer(s) to the race question. RACE provides the full detail given by the respondent and/or released by the Census Bureau; it is not always historically compatible (see comparability discussion below). Users primarily interested in historical compatibility should consider using RACHSING. RACHSING codes race and Hispanic origin responses into a simple, historically compatible scheme that includes only federally defined race and Hispanic origin groups. Please note that RACESING, an earlier version of RACHSING, is also available on the IPUMS website. 

In addition, specific combinations of major races can be discerned using the following bivariate indicators of whether a particular race group was reported: RACAMIND, RACASIAN, RACBLK, RACOTHER, RACPACIS, and RACWHT. RACNUM indicates the total number of major race groups reported for an individual. The information contained in the bivariate indicators and in RACNUM is integrated into the detailed version of RACE. 

Prior to 1960, the census enumerator was responsible for categorizing persons and was not specifically instructed to ask the individual his or her race. In 1970 and later years, an individual's race was reported by someone in the household or group quarters. In the 1990 U.S. census, the 2000 U.S. and Puerto Rican censuses, the ACS, and the PRCS respondents were specifically asked what race the person "considers himself/herself" to be, although such self-description was more or less operative since 1960.

User Note: Race questions were not asked in the Puerto Rican censuses of 1970, 1980, and 1990.  They were asked in the 1910 and 1920 Puerto Rican censuses, the 2000-2010 Puerto Rican censuses, and the PRCS.]]></txt>
      <catgry>
        <catValu>100</catValu>
        <labl>White</labl>
      </catgry>
      <catgry>
        <catValu>110</catValu>
        <labl>Spanish write_in</labl>
      </catgry>
      <catgry>
        <catValu>120</catValu>
        <labl>Blank (white) (1850)</labl>
      </catgry>
      <catgry>
        <catValu>130</catValu>
        <labl>Portuguese</labl>
      </catgry>
      <catgry>
        <catValu>140</catValu>
        <labl>Mexican (1930)</labl>
      </catgry>
      <catgry>
        <catValu>150</catValu>
        <labl>Puerto Rican (1910 Hawaii)</labl>
      </catgry>
      <catgry>
        <catValu>200</catValu>
        <labl>Black/African American</labl>
      </catgry>
      <catgry>
        <catValu>210</catValu>
        <labl>Mulatto</labl>
      </catgry>
      <catgry>
        <catValu>300</catValu>
        <labl>American Indian/Alaska Native</labl>
      </catgry>
      <catgry>
        <catValu>302</catValu>
        <labl>Apache</labl>
      </catgry>
      <catgry>
        <catValu>303</catValu>
        <labl>Blackfoot</labl>
      </catgry>
      <catgry>
        <catValu>304</catValu>
        <labl>Cherokee</labl>
      </catgry>
      <catgry>
        <catValu>305</catValu>
        <labl>Cheyenne</labl>
      </catgry>
      <catgry>
        <catValu>306</catValu>
        <labl>Chickasaw</labl>
      </catgry>
      <catgry>
        <catValu>307</catValu>
        <labl>Chippewa</labl>
      </catgry>
      <catgry>
        <catValu>308</catValu>
        <labl>Choctaw</labl>
      </catgry>
      <catgry>
        <catValu>309</catValu>
        <labl>Comanche</labl>
      </catgry>
      <catgry>
        <catValu>310</catValu>
        <labl>Creek</labl>
      </catgry>
      <catgry>
        <catValu>311</catValu>
        <labl>Crow</labl>
      </catgry>
      <catgry>
        <catValu>312</catValu>
        <labl>Iroquois</labl>
      </catgry>
      <catgry>
        <catValu>313</catValu>
        <labl>Kiowa</labl>
      </catgry>
      <catgry>
        <catValu>314</catValu>
        <labl>Lumbee</labl>
      </catgry>
      <catgry>
        <catValu>315</catValu>
        <labl>Navajo</labl>
      </catgry>
      <catgry>
        <catValu>316</catValu>
        <labl>Osage</labl>
      </catgry>
      <catgry>
        <catValu>317</catValu>
        <labl>Paiute</labl>
      </catgry>
      <catgry>
        <catValu>318</catValu>
        <labl>Pima</labl>
      </catgry>
      <catgry>
        <catValu>319</catValu>
        <labl>Potawatomi</labl>
      </catgry>
      <catgry>
        <catValu>320</catValu>
        <labl>Pueblo</labl>
      </catgry>
      <catgry>
        <catValu>321</catValu>
        <labl>Seminole</labl>
      </catgry>
      <catgry>
        <catValu>322</catValu>
        <labl>Shoshone</labl>
      </catgry>
      <catgry>
        <catValu>323</catValu>
        <labl>Sioux</labl>
      </catgry>
      <catgry>
        <catValu>324</catValu>
        <labl>Tlingit (Tlingit_Haida, 2000/ACS)</labl>
      </catgry>
      <catgry>
        <catValu>325</catValu>
        <labl>Tohono O Odham</labl>
      </catgry>
      <catgry>
        <catValu>326</catValu>
        <labl>All other tribes (1990)</labl>
      </catgry>
      <catgry>
        <catValu>328</catValu>
        <labl>Hopi</labl>
      </catgry>
      <catgry>
        <catValu>329</catValu>
        <labl>Central American Indian</labl>
      </catgry>
      <catgry>
        <catValu>330</catValu>
        <labl>Spanish American Indian</labl>
      </catgry>
      <catgry>
        <catValu>350</catValu>
        <labl>Delaware</labl>
      </catgry>
      <catgry>
        <catValu>351</catValu>
        <labl>Latin American Indian</labl>
      </catgry>
      <catgry>
        <catValu>352</catValu>
        <labl>Puget Sound Salish</labl>
      </catgry>
      <catgry>
        <catValu>353</catValu>
        <labl>Yakama</labl>
      </catgry>
      <catgry>
        <catValu>354</catValu>
        <labl>Yaqui</labl>
      </catgry>
      <catgry>
        <catValu>355</catValu>
        <labl>Colville</labl>
      </catgry>
      <catgry>
        <catValu>356</catValu>
        <labl>Houma</labl>
      </catgry>
      <catgry>
        <catValu>357</catValu>
        <labl>Menominee</labl>
      </catgry>
      <catgry>
        <catValu>358</catValu>
        <labl>Yuman</labl>
      </catgry>
      <catgry>
        <catValu>359</catValu>
        <labl>South American Indian</labl>
      </catgry>
      <catgry>
        <catValu>360</catValu>
        <labl>Mexican American Indian</labl>
      </catgry>
      <catgry>
        <catValu>361</catValu>
        <labl>Other Amer. Indian tribe (2000,ACS)</labl>
      </catgry>
      <catgry>
        <catValu>362</catValu>
        <labl>2+ Amer. Indian tribes (2000,ACS)</labl>
      </catgry>
      <catgry>
        <catValu>370</catValu>
        <labl>Alaskan Athabaskan</labl>
      </catgry>
      <catgry>
        <catValu>371</catValu>
        <labl>Aleut</labl>
      </catgry>
      <catgry>
        <catValu>372</catValu>
        <labl>Eskimo</labl>
      </catgry>
      <catgry>
        <catValu>373</catValu>
        <labl>Alaskan mixed</labl>
      </catgry>
      <catgry>
        <catValu>374</catValu>
        <labl>Inupiat</labl>
      </catgry>
      <catgry>
        <catValu>375</catValu>
        <labl>Yup'ik</labl>
      </catgry>
      <catgry>
        <catValu>379</catValu>
        <labl>Other Alaska Native tribe(s) (2000,ACS)</labl>
      </catgry>
      <catgry>
        <catValu>398</catValu>
        <labl>Both Am. Ind. and Alaska Native (2000,ACS)</labl>
      </catgry>
      <catgry>
        <catValu>399</catValu>
        <labl>Tribe not specified</labl>
      </catgry>
      <catgry>
        <catValu>400</catValu>
        <labl>Chinese</labl>
      </catgry>
      <catgry>
        <catValu>410</catValu>
        <labl>Taiwanese</labl>
      </catgry>
      <catgry>
        <catValu>420</catValu>
        <labl>Chinese and Taiwanese</labl>
      </catgry>
      <catgry>
        <catValu>500</catValu>
        <labl>Japanese</labl>
      </catgry>
      <catgry>
        <catValu>600</catValu>
        <labl>Filipino</labl>
      </catgry>
      <catgry>
        <catValu>610</catValu>
        <labl>Asian Indian (Hindu 1920_1940)</labl>
      </catgry>
      <catgry>
        <catValu>620</catValu>
        <labl>Korean</labl>
      </catgry>
      <catgry>
        <catValu>630</catValu>
        <labl>Hawaiian</labl>
      </catgry>
      <catgry>
        <catValu>631</catValu>
        <labl>Hawaiian and Asian (1900,1920)</labl>
      </catgry>
      <catgry>
        <catValu>632</catValu>
        <labl>Hawaiian and European (1900,1920)</labl>
      </catgry>
      <catgry>
        <catValu>634</catValu>
        <labl>Hawaiian mixed</labl>
      </catgry>
      <catgry>
        <catValu>640</catValu>
        <labl>Vietnamese</labl>
      </catgry>
      <catgry>
        <catValu>641</catValu>
        <labl>Bhutanese</labl>
      </catgry>
      <catgry>
        <catValu>642</catValu>
        <labl>Mongolian</labl>
      </catgry>
      <catgry>
        <catValu>643</catValu>
        <labl>Nepalese</labl>
      </catgry>
      <catgry>
        <catValu>650</catValu>
        <labl>Other Asian or Pacific Islander (1920,1980)</labl>
      </catgry>
      <catgry>
        <catValu>651</catValu>
        <labl>Asian only (CPS)</labl>
      </catgry>
      <catgry>
        <catValu>652</catValu>
        <labl>Pacific Islander only (CPS)</labl>
      </catgry>
      <catgry>
        <catValu>653</catValu>
        <labl>Asian or Pacific Islander, n.s. (1990 Internal Census files)</labl>
      </catgry>
      <catgry>
        <catValu>660</catValu>
        <labl>Cambodian</labl>
      </catgry>
      <catgry>
        <catValu>661</catValu>
        <labl>Hmong</labl>
      </catgry>
      <catgry>
        <catValu>662</catValu>
        <labl>Laotian</labl>
      </catgry>
      <catgry>
        <catValu>663</catValu>
        <labl>Thai</labl>
      </catgry>
      <catgry>
        <catValu>664</catValu>
        <labl>Bangladeshi</labl>
      </catgry>
      <catgry>
        <catValu>665</catValu>
        <labl>Burmese</labl>
      </catgry>
      <catgry>
        <catValu>666</catValu>
        <labl>Indonesian</labl>
      </catgry>
      <catgry>
        <catValu>667</catValu>
        <labl>Malaysian</labl>
      </catgry>
      <catgry>
        <catValu>668</catValu>
        <labl>Okinawan</labl>
      </catgry>
      <catgry>
        <catValu>669</catValu>
        <labl>Pakistani</labl>
      </catgry>
      <catgry>
        <catValu>670</catValu>
        <labl>Sri Lankan</labl>
      </catgry>
      <catgry>
        <catValu>671</catValu>
        <labl>Other Asian, n.e.c.</labl>
      </catgry>
      <catgry>
        <catValu>672</catValu>
        <labl>Asian, not specified</labl>
      </catgry>
      <catgry>
        <catValu>673</catValu>
        <labl>Chinese and Japanese</labl>
      </catgry>
      <catgry>
        <catValu>674</catValu>
        <labl>Chinese and Filipino</labl>
      </catgry>
      <catgry>
        <catValu>675</catValu>
        <labl>Chinese and Vietnamese</labl>
      </catgry>
      <catgry>
        <catValu>676</catValu>
        <labl>Chinese and Asian write_in</labl>
      </catgry>
      <catgry>
        <catValu>677</catValu>
        <labl>Japanese and Filipino</labl>
      </catgry>
      <catgry>
        <catValu>678</catValu>
        <labl>Asian Indian and Asian write_in</labl>
      </catgry>
      <catgry>
        <catValu>679</catValu>
        <labl>Other Asian race combinations</labl>
      </catgry>
      <catgry>
        <catValu>680</catValu>
        <labl>Samoan</labl>
      </catgry>
      <catgry>
        <catValu>681</catValu>
        <labl>Tahitian</labl>
      </catgry>
      <catgry>
        <catValu>682</catValu>
        <labl>Tongan</labl>
      </catgry>
      <catgry>
        <catValu>683</catValu>
        <labl>Other Polynesian (1990)</labl>
      </catgry>
      <catgry>
        <catValu>684</catValu>
        <labl>1+ other Polynesian races (2000,ACS)</labl>
      </catgry>
      <catgry>
        <catValu>685</catValu>
        <labl>Chamorro</labl>
      </catgry>
      <catgry>
        <catValu>686</catValu>
        <labl>Northern Mariana Islander</labl>
      </catgry>
      <catgry>
        <catValu>687</catValu>
        <labl>Palauan</labl>
      </catgry>
      <catgry>
        <catValu>688</catValu>
        <labl>Other Micronesian (1990)</labl>
      </catgry>
      <catgry>
        <catValu>689</catValu>
        <labl>1+ other Micronesian races (2000,ACS)</labl>
      </catgry>
      <catgry>
        <catValu>690</catValu>
        <labl>Fijian</labl>
      </catgry>
      <catgry>
        <catValu>691</catValu>
        <labl>Other Melanesian (1990)</labl>
      </catgry>
      <catgry>
        <catValu>692</catValu>
        <labl>1+ other Melanesian races (2000,ACS)</labl>
      </catgry>
      <catgry>
        <catValu>698</catValu>
        <labl>2+ PI races from 2+ PI regions</labl>
      </catgry>
      <catgry>
        <catValu>699</catValu>
        <labl>Pacific Islander, n.s.</labl>
      </catgry>
      <catgry>
        <catValu>700</catValu>
        <labl>Other race, n.e.c.</labl>
      </catgry>
      <catgry>
        <catValu>801</catValu>
        <labl>White and Black</labl>
      </catgry>
      <catgry>
        <catValu>802</catValu>
        <labl>White and AIAN</labl>
      </catgry>
      <catgry>
        <catValu>810</catValu>
        <labl>White and Asian</labl>
      </catgry>
      <catgry>
        <catValu>811</catValu>
        <labl>White and Chinese</labl>
      </catgry>
      <catgry>
        <catValu>812</catValu>
        <labl>White and Japanese</labl>
      </catgry>
      <catgry>
        <catValu>813</catValu>
        <labl>White and Filipino</labl>
      </catgry>
      <catgry>
        <catValu>814</catValu>
        <labl>White and Asian Indian</labl>
      </catgry>
      <catgry>
        <catValu>815</catValu>
        <labl>White and Korean</labl>
      </catgry>
      <catgry>
        <catValu>816</catValu>
        <labl>White and Vietnamese</labl>
      </catgry>
      <catgry>
        <catValu>817</catValu>
        <labl>White and Asian write_in</labl>
      </catgry>
      <catgry>
        <catValu>818</catValu>
        <labl>White and other Asian race(s)</labl>
      </catgry>
      <catgry>
        <catValu>819</catValu>
        <labl>White and two or more Asian groups</labl>
      </catgry>
      <catgry>
        <catValu>820</catValu>
        <labl>White and PI</labl>
      </catgry>
      <catgry>
        <catValu>821</catValu>
        <labl>White and Native Hawaiian</labl>
      </catgry>
      <catgry>
        <catValu>822</catValu>
        <labl>White and Samoan</labl>
      </catgry>
      <catgry>
        <catValu>823</catValu>
        <labl>White and Chamorro</labl>
      </catgry>
      <catgry>
        <catValu>824</catValu>
        <labl>White and PI write_in</labl>
      </catgry>
      <catgry>
        <catValu>825</catValu>
        <labl>White and other PI race(s)</labl>
      </catgry>
      <catgry>
        <catValu>826</catValu>
        <labl>White and other race write_in</labl>
      </catgry>
      <catgry>
        <catValu>827</catValu>
        <labl>White and other race, n.e.c.</labl>
      </catgry>
      <catgry>
        <catValu>830</catValu>
        <labl>Black and AIAN</labl>
      </catgry>
      <catgry>
        <catValu>831</catValu>
        <labl>Black and Asian</labl>
      </catgry>
      <catgry>
        <catValu>832</catValu>
        <labl>Black and Chinese</labl>
      </catgry>
      <catgry>
        <catValu>833</catValu>
        <labl>Black and Japanese</labl>
      </catgry>
      <catgry>
        <catValu>834</catValu>
        <labl>Black and Filipino</labl>
      </catgry>
      <catgry>
        <catValu>835</catValu>
        <labl>Black and Asian Indian</labl>
      </catgry>
      <catgry>
        <catValu>836</catValu>
        <labl>Black and Korean</labl>
      </catgry>
      <catgry>
        <catValu>837</catValu>
        <labl>Black and Asian write_in</labl>
      </catgry>
      <catgry>
        <catValu>838</catValu>
        <labl>Black and other Asian race(s)</labl>
      </catgry>
      <catgry>
        <catValu>840</catValu>
        <labl>Black and PI</labl>
      </catgry>
      <catgry>
        <catValu>841</catValu>
        <labl>Black and PI write_in</labl>
      </catgry>
      <catgry>
        <catValu>842</catValu>
        <labl>Black and other PI race(s)</labl>
      </catgry>
      <catgry>
        <catValu>845</catValu>
        <labl>Black and other race write_in</labl>
      </catgry>
      <catgry>
        <catValu>850</catValu>
        <labl>AIAN and Asian</labl>
      </catgry>
      <catgry>
        <catValu>851</catValu>
        <labl>AIAN and Filipino (2000 1%)</labl>
      </catgry>
      <catgry>
        <catValu>852</catValu>
        <labl>AIAN and Asian Indian</labl>
      </catgry>
      <catgry>
        <catValu>853</catValu>
        <labl>AIAN and Asian write_in (2000 1%)</labl>
      </catgry>
      <catgry>
        <catValu>854</catValu>
        <labl>AIAN and other Asian race(s)</labl>
      </catgry>
      <catgry>
        <catValu>855</catValu>
        <labl>AIAN and PI</labl>
      </catgry>
      <catgry>
        <catValu>856</catValu>
        <labl>AIAN and other race write_in</labl>
      </catgry>
      <catgry>
        <catValu>860</catValu>
        <labl>Asian and PI</labl>
      </catgry>
      <catgry>
        <catValu>861</catValu>
        <labl>Chinese and Hawaiian</labl>
      </catgry>
      <catgry>
        <catValu>862</catValu>
        <labl>Chinese, Filipino, Hawaiian (2000 1%)</labl>
      </catgry>
      <catgry>
        <catValu>863</catValu>
        <labl>Japanese and Hawaiian (2000 1%)</labl>
      </catgry>
      <catgry>
        <catValu>864</catValu>
        <labl>Filipino and Hawaiian</labl>
      </catgry>
      <catgry>
        <catValu>865</catValu>
        <labl>Filipino and PI write_in</labl>
      </catgry>
      <catgry>
        <catValu>866</catValu>
        <labl>Asian Indian and PI write_in (2000 1%)</labl>
      </catgry>
      <catgry>
        <catValu>867</catValu>
        <labl>Asian write_in and PI write_in</labl>
      </catgry>
      <catgry>
        <catValu>868</catValu>
        <labl>Other Asian race(s) and PI race(s)</labl>
      </catgry>
      <catgry>
        <catValu>869</catValu>
        <labl>Japanese and Korean (ACS)</labl>
      </catgry>
      <catgry>
        <catValu>880</catValu>
        <labl>Asian and other race write_in</labl>
      </catgry>
      <catgry>
        <catValu>881</catValu>
        <labl>Chinese and other race write_in</labl>
      </catgry>
      <catgry>
        <catValu>882</catValu>
        <labl>Japanese and other race write_in</labl>
      </catgry>
      <catgry>
        <catValu>883</catValu>
        <labl>Filipino and other race write_in</labl>
      </catgry>
      <catgry>
        <catValu>884</catValu>
        <labl>Asian Indian and other race write_in</labl>
      </catgry>
      <catgry>
        <catValu>885</catValu>
        <labl>Asian write_in and other race write_in</labl>
      </catgry>
      <catgry>
        <catValu>886</catValu>
        <labl>Other Asian race(s) and other race write_in</labl>
      </catgry>
      <catgry>
        <catValu>887</catValu>
        <labl>Chinese and Korean</labl>
      </catgry>
      <catgry>
        <catValu>890</catValu>
        <labl>PI and other race write_in:</labl>
      </catgry>
      <catgry>
        <catValu>891</catValu>
        <labl>PI write_in and other race write_in</labl>
      </catgry>
      <catgry>
        <catValu>892</catValu>
        <labl>Other PI race(s) and other race write_in</labl>
      </catgry>
      <catgry>
        <catValu>893</catValu>
        <labl>Native Hawaiian or PI other race(s)</labl>
      </catgry>
      <catgry>
        <catValu>899</catValu>
        <labl>API and other race write_in</labl>
      </catgry>
      <catgry>
        <catValu>901</catValu>
        <labl>White, Black, AIAN</labl>
      </catgry>
      <catgry>
        <catValu>902</catValu>
        <labl>White, Black, Asian</labl>
      </catgry>
      <catgry>
        <catValu>903</catValu>
        <labl>White, Black, PI</labl>
      </catgry>
      <catgry>
        <catValu>904</catValu>
        <labl>White, Black, other race write_in</labl>
      </catgry>
      <catgry>
        <catValu>905</catValu>
        <labl>White, AIAN, Asian</labl>
      </catgry>
      <catgry>
        <catValu>906</catValu>
        <labl>White, AIAN, PI</labl>
      </catgry>
      <catgry>
        <catValu>907</catValu>
        <labl>White, AIAN, other race write_in</labl>
      </catgry>
      <catgry>
        <catValu>910</catValu>
        <labl>White, Asian, PI</labl>
      </catgry>
      <catgry>
        <catValu>911</catValu>
        <labl>White, Chinese, Hawaiian</labl>
      </catgry>
      <catgry>
        <catValu>912</catValu>
        <labl>White, Chinese, Filipino, Hawaiian (2000 1%)</labl>
      </catgry>
      <catgry>
        <catValu>913</catValu>
        <labl>White, Japanese, Hawaiian (2000 1%)</labl>
      </catgry>
      <catgry>
        <catValu>914</catValu>
        <labl>White, Filipino, Hawaiian</labl>
      </catgry>
      <catgry>
        <catValu>915</catValu>
        <labl>Other White, Asian race(s), PI race(s)</labl>
      </catgry>
      <catgry>
        <catValu>916</catValu>
        <labl>White, AIAN and Filipino</labl>
      </catgry>
      <catgry>
        <catValu>917</catValu>
        <labl>White, Black, and Filipino</labl>
      </catgry>
      <catgry>
        <catValu>920</catValu>
        <labl>White, Asian, other race write_in</labl>
      </catgry>
      <catgry>
        <catValu>921</catValu>
        <labl>White, Filipino, other race write_in (2000 1%)</labl>
      </catgry>
      <catgry>
        <catValu>922</catValu>
        <labl>White, Asian write_in, other race write_in (2000 1%)</labl>
      </catgry>
      <catgry>
        <catValu>923</catValu>
        <labl>Other White, Asian race(s), other race write_in (2000 1%)</labl>
      </catgry>
      <catgry>
        <catValu>925</catValu>
        <labl>White, PI, other race write_in</labl>
      </catgry>
      <catgry>
        <catValu>930</catValu>
        <labl>Black, AIAN, Asian</labl>
      </catgry>
      <catgry>
        <catValu>931</catValu>
        <labl>Black, AIAN, PI</labl>
      </catgry>
      <catgry>
        <catValu>932</catValu>
        <labl>Black, AIAN, other race write_in</labl>
      </catgry>
      <catgry>
        <catValu>933</catValu>
        <labl>Black, Asian, PI</labl>
      </catgry>
      <catgry>
        <catValu>934</catValu>
        <labl>Black, Asian, other race write_in</labl>
      </catgry>
      <catgry>
        <catValu>935</catValu>
        <labl>Black, PI, other race write_in</labl>
      </catgry>
      <catgry>
        <catValu>940</catValu>
        <labl>AIAN, Asian, PI</labl>
      </catgry>
      <catgry>
        <catValu>941</catValu>
        <labl>AIAN, Asian, other race write_in</labl>
      </catgry>
      <catgry>
        <catValu>942</catValu>
        <labl>AIAN, PI, other race write_in</labl>
      </catgry>
      <catgry>
        <catValu>943</catValu>
        <labl>Asian, PI, other race write_in</labl>
      </catgry>
      <catgry>
        <catValu>944</catValu>
        <labl>Asian (Chinese, Japanese, Korean, Vietnamese); and Native Hawaiian or PI; and Other</labl>
      </catgry>
      <catgry>
        <catValu>949</catValu>
        <labl>2 or 3 races (CPS)</labl>
      </catgry>
      <catgry>
        <catValu>950</catValu>
        <labl>White, Black, AIAN, Asian</labl>
      </catgry>
      <catgry>
        <catValu>951</catValu>
        <labl>White, Black, AIAN, PI</labl>
      </catgry>
      <catgry>
        <catValu>952</catValu>
        <labl>White, Black, AIAN, other race write_in</labl>
      </catgry>
      <catgry>
        <catValu>953</catValu>
        <labl>White, Black, Asian, PI</labl>
      </catgry>
      <catgry>
        <catValu>954</catValu>
        <labl>White, Black, Asian, other race write_in</labl>
      </catgry>
      <catgry>
        <catValu>955</catValu>
        <labl>White, Black, PI, other race write_in</labl>
      </catgry>
      <catgry>
        <catValu>960</catValu>
        <labl>White, AIAN, Asian, PI</labl>
      </catgry>
      <catgry>
        <catValu>961</catValu>
        <labl>White, AIAN, Asian, other race write_in</labl>
      </catgry>
      <catgry>
        <catValu>962</catValu>
        <labl>White, AIAN, PI, other race write_in</labl>
      </catgry>
      <catgry>
        <catValu>963</catValu>
        <labl>White, Asian, PI, other race write_in</labl>
      </catgry>
      <catgry>
        <catValu>964</catValu>
        <labl>White, Chinese, Japanese, Native Hawaiian</labl>
      </catgry>
      <catgry>
        <catValu>970</catValu>
        <labl>Black, AIAN, Asian, PI</labl>
      </catgry>
      <catgry>
        <catValu>971</catValu>
        <labl>Black, AIAN, Asian, other race write_in</labl>
      </catgry>
      <catgry>
        <catValu>972</catValu>
        <labl>Black, AIAN, PI, other race write_in</labl>
      </catgry>
      <catgry>
        <catValu>973</catValu>
        <labl>Black, Asian, PI, other race write_in</labl>
      </catgry>
      <catgry>
        <catValu>974</catValu>
        <labl>AIAN, Asian, PI, other race write_in</labl>
      </catgry>
      <catgry>
        <catValu>975</catValu>
        <labl>AIAN, Asian, PI, Hawaiian other race write_in</labl>
      </catgry>
      <catgry>
        <catValu>976</catValu>
        <labl>Two specified Asian  (Chinese and other Asian, Chinese and Japanese, Japanese and other Asian, Korean and other Asian); Native Hawaiian/PI; and Other Race</labl>
      </catgry>
      <catgry>
        <catValu>980</catValu>
        <labl>White, Black, AIAN, Asian, PI</labl>
      </catgry>
      <catgry>
        <catValu>981</catValu>
        <labl>White, Black, AIAN, Asian, other race write_in</labl>
      </catgry>
      <catgry>
        <catValu>982</catValu>
        <labl>White, Black, AIAN, PI, other race write_in</labl>
      </catgry>
      <catgry>
        <catValu>983</catValu>
        <labl>White, Black, Asian, PI, other race write_in</labl>
      </catgry>
      <catgry>
        <catValu>984</catValu>
        <labl>White, AIAN, Asian, PI, other race write_in</labl>
      </catgry>
      <catgry>
        <catValu>985</catValu>
        <labl>Black, AIAN, Asian, PI, other race write_in</labl>
      </catgry>
      <catgry>
        <catValu>986</catValu>
        <labl>Black, AIAN, Asian, PI, Hawaiian, other race write_in</labl>
      </catgry>
      <catgry>
        <catValu>989</catValu>
        <labl>4 or 5 races (CPS)</labl>
      </catgry>
      <catgry>
        <catValu>990</catValu>
        <labl>White, Black, AIAN, Asian, PI, other race write_in</labl>
      </catgry>
      <catgry>
        <catValu>991</catValu>
        <labl>White race; Some other race; Black or African American race and/or American Indian and Alaska Native race and/or Asian groups and/or Native Hawaiian and Other Pacific Islander groups</labl>
      </catgry>
      <catgry>
        <catValu>996</catValu>
        <labl>2+ races, n.e.c. (CPS)</labl>
      </catgry>
      <concept vocab="IPUMS">Race, Ethnicity, and Nativity Variables -- PERSON</concept>
      <varFormat schema="other" type="numeric"/>
    </var>
    <var ID="HISPAN" dcml="0" files="ExtractData" intrvl="discrete" name="HISPAN">
      <location EndPos="21" StartPos="21" width="1"/>
      <labl>Hispanic origin [general version]</labl>
      <txt><![CDATA[HISPAN identifies persons of Hispanic/Spanish/Latino origin and classifies them according to their country of origin when possible. Origin is defined by the Census Bureau as ancestry, lineage, heritage, nationality group, or country of birth. People of Hispanic origin may be of any race; see RACE for a discussion of coding issues involved.  Users should note that race questions were not asked in the Puerto Rican censuses of 1970, 1980 and 1990.  They were asked in the 1910 and 1920 Puerto Rican censuses, and in the 2000 and 2010 Puerto Rican census and the PRCS.  However, questions assessing Spanish/Hispanic origin were not asked in the Puerto Rican censuses prior to 2000. 

The HISPAN general code covers country-of-origin classifications common to all years; the detailed code distinguishes additional groups and subgroups. See HISPRULE for details on how country of origin information was assigned prior to 1980. 

In 2020, the Census Bureau updated the questionnaire text, processing, and coding of the race and Hispanic origin questions, resulting in major changes to the distribution of race and Hispanic origin categories. As a result, users should proceed with caution when comparing HISPAN and RACE in 2019-prior samples with 2020-onward samples. See the comparability tab for more details.]]></txt>
      <catgry>
        <catValu>0</catValu>
        <labl>Not Hispanic</labl>
      </catgry>
      <catgry>
        <catValu>1</catValu>
        <labl>Mexican</labl>
      </catgry>
      <catgry>
        <catValu>2</catValu>
        <labl>Puerto Rican</labl>
      </catgry>
      <catgry>
        <catValu>3</catValu>
        <labl>Cuban</labl>
      </catgry>
      <catgry>
        <catValu>4</catValu>
        <labl>Other</labl>
      </catgry>
      <catgry>
        <catValu>9</catValu>
        <labl>Not Reported</labl>
      </catgry>
      <concept vocab="IPUMS">Race, Ethnicity, and Nativity Variables -- PERSON</concept>
      <varFormat schema="other" type="numeric"/>
    </var>
    <var ID="HISPAND" dcml="0" files="ExtractData" intrvl="discrete" name="HISPAND">
      <location EndPos="24" StartPos="22" width="3"/>
      <labl>Hispanic origin [detailed version]</labl>
      <txt><![CDATA[HISPAN identifies persons of Hispanic/Spanish/Latino origin and classifies them according to their country of origin when possible. Origin is defined by the Census Bureau as ancestry, lineage, heritage, nationality group, or country of birth. People of Hispanic origin may be of any race; see RACE for a discussion of coding issues involved.  Users should note that race questions were not asked in the Puerto Rican censuses of 1970, 1980 and 1990.  They were asked in the 1910 and 1920 Puerto Rican censuses, and in the 2000 and 2010 Puerto Rican census and the PRCS.  However, questions assessing Spanish/Hispanic origin were not asked in the Puerto Rican censuses prior to 2000. 

The HISPAN general code covers country-of-origin classifications common to all years; the detailed code distinguishes additional groups and subgroups. See HISPRULE for details on how country of origin information was assigned prior to 1980. 

In 2020, the Census Bureau updated the questionnaire text, processing, and coding of the race and Hispanic origin questions, resulting in major changes to the distribution of race and Hispanic origin categories. As a result, users should proceed with caution when comparing HISPAN and RACE in 2019-prior samples with 2020-onward samples. See the comparability tab for more details.]]></txt>
      <catgry>
        <catValu>000</catValu>
        <labl>Not Hispanic</labl>
      </catgry>
      <catgry>
        <catValu>100</catValu>
        <labl>Mexican</labl>
      </catgry>
      <catgry>
        <catValu>102</catValu>
        <labl>Mexican American</labl>
      </catgry>
      <catgry>
        <catValu>103</catValu>
        <labl>Mexicano/Mexicana</labl>
      </catgry>
      <catgry>
        <catValu>104</catValu>
        <labl>Chicano/Chicana</labl>
      </catgry>
      <catgry>
        <catValu>105</catValu>
        <labl>La Raza</labl>
      </catgry>
      <catgry>
        <catValu>106</catValu>
        <labl>Mexican American Indian</labl>
      </catgry>
      <catgry>
        <catValu>107</catValu>
        <labl>Mexico</labl>
      </catgry>
      <catgry>
        <catValu>200</catValu>
        <labl>Puerto Rican</labl>
      </catgry>
      <catgry>
        <catValu>300</catValu>
        <labl>Cuban</labl>
      </catgry>
      <catgry>
        <catValu>401</catValu>
        <labl>Central American Indian</labl>
      </catgry>
      <catgry>
        <catValu>402</catValu>
        <labl>Canal Zone</labl>
      </catgry>
      <catgry>
        <catValu>411</catValu>
        <labl>Costa Rican</labl>
      </catgry>
      <catgry>
        <catValu>412</catValu>
        <labl>Guatemalan</labl>
      </catgry>
      <catgry>
        <catValu>413</catValu>
        <labl>Honduran</labl>
      </catgry>
      <catgry>
        <catValu>414</catValu>
        <labl>Nicaraguan</labl>
      </catgry>
      <catgry>
        <catValu>415</catValu>
        <labl>Panamanian</labl>
      </catgry>
      <catgry>
        <catValu>416</catValu>
        <labl>Salvadoran</labl>
      </catgry>
      <catgry>
        <catValu>417</catValu>
        <labl>Central American, n.e.c.</labl>
      </catgry>
      <catgry>
        <catValu>420</catValu>
        <labl>Argentinean</labl>
      </catgry>
      <catgry>
        <catValu>421</catValu>
        <labl>Bolivian</labl>
      </catgry>
      <catgry>
        <catValu>422</catValu>
        <labl>Chilean</labl>
      </catgry>
      <catgry>
        <catValu>423</catValu>
        <labl>Colombian</labl>
      </catgry>
      <catgry>
        <catValu>424</catValu>
        <labl>Ecuadorian</labl>
      </catgry>
      <catgry>
        <catValu>425</catValu>
        <labl>Paraguayan</labl>
      </catgry>
      <catgry>
        <catValu>426</catValu>
        <labl>Peruvian</labl>
      </catgry>
      <catgry>
        <catValu>427</catValu>
        <labl>Uruguayan</labl>
      </catgry>
      <catgry>
        <catValu>428</catValu>
        <labl>Venezuelan</labl>
      </catgry>
      <catgry>
        <catValu>429</catValu>
        <labl>South American Indian</labl>
      </catgry>
      <catgry>
        <catValu>430</catValu>
        <labl>Criollo</labl>
      </catgry>
      <catgry>
        <catValu>431</catValu>
        <labl>South American, n.e.c.</labl>
      </catgry>
      <catgry>
        <catValu>450</catValu>
        <labl>Spaniard</labl>
      </catgry>
      <catgry>
        <catValu>451</catValu>
        <labl>Andalusian</labl>
      </catgry>
      <catgry>
        <catValu>452</catValu>
        <labl>Asturian</labl>
      </catgry>
      <catgry>
        <catValu>453</catValu>
        <labl>Castillian</labl>
      </catgry>
      <catgry>
        <catValu>454</catValu>
        <labl>Catalonian</labl>
      </catgry>
      <catgry>
        <catValu>455</catValu>
        <labl>Balearic Islander</labl>
      </catgry>
      <catgry>
        <catValu>456</catValu>
        <labl>Gallego</labl>
      </catgry>
      <catgry>
        <catValu>457</catValu>
        <labl>Valencian</labl>
      </catgry>
      <catgry>
        <catValu>458</catValu>
        <labl>Canarian</labl>
      </catgry>
      <catgry>
        <catValu>459</catValu>
        <labl>Spanish Basque</labl>
      </catgry>
      <catgry>
        <catValu>460</catValu>
        <labl>Dominican</labl>
      </catgry>
      <catgry>
        <catValu>465</catValu>
        <labl>Latin American</labl>
      </catgry>
      <catgry>
        <catValu>470</catValu>
        <labl>Hispanic</labl>
      </catgry>
      <catgry>
        <catValu>480</catValu>
        <labl>Spanish</labl>
      </catgry>
      <catgry>
        <catValu>490</catValu>
        <labl>Californio</labl>
      </catgry>
      <catgry>
        <catValu>491</catValu>
        <labl>Tejano</labl>
      </catgry>
      <catgry>
        <catValu>492</catValu>
        <labl>Nuevo Mexicano</labl>
      </catgry>
      <catgry>
        <catValu>493</catValu>
        <labl>Spanish American</labl>
      </catgry>
      <catgry>
        <catValu>494</catValu>
        <labl>Spanish American Indian</labl>
      </catgry>
      <catgry>
        <catValu>495</catValu>
        <labl>Meso American Indian</labl>
      </catgry>
      <catgry>
        <catValu>496</catValu>
        <labl>Mestizo</labl>
      </catgry>
      <catgry>
        <catValu>498</catValu>
        <labl>Other, n.s.</labl>
      </catgry>
      <catgry>
        <catValu>499</catValu>
        <labl>Other, n.e.c.</labl>
      </catgry>
      <catgry>
        <catValu>900</catValu>
        <labl>Not Reported</labl>
      </catgry>
      <concept vocab="IPUMS">Race, Ethnicity, and Nativity Variables -- PERSON</concept>
      <varFormat schema="other" type="numeric"/>
    </var>
    <var ID="INDNAICS" dcml="0" files="ExtractData" intrvl="contin" name="INDNAICS">
      <location EndPos="32" StartPos="25" width="8"/>
      <labl>Industry, NAICS classification</labl>
      <txt><![CDATA[INDNAICS reports the type of establishment in which the person worked, in terms of the good or service produced. INDNAICS codes industries according to the North American Industrial Classification System, which was developed in 1997. This categorization system is substantially different from industry classifications used in prior years. 

For workers employed during the previous week, the data refer to the job at which the person worked the greatest number of hours. For unemployed persons or those out of the labor force, the data refer to their most recent job, if it was within the previous five years.

The variable IND provides a numeric industry classification that is closely related to the INDNAICS scheme. The crosswalk between the IND and INDNAICS codes are available here: 

IND to INDNAICS Crosswalk

User Caution: INDNAICS contains alphabetic characters (See IND for a fully numeric classification of industry).

Note: The IND to INDNAICS crosswalk is reflective of the codes in the ACS PUMS data files, which slightly differ from the codes found here: Full list of Census provided Industry and Occupation Codes.]]></txt>
      <codInstr><![CDATA[CodesINDNAICS is an 8-digit alphanumeric string variable which reports the type of establishment in which the person worked, in terms of the good or service produced. INDNAICS codes industries according to the North American Industrial Classification System, which was developed in 1997. This categorization system is substantially different from industry classifications used in prior years. A crosswalk of INDNAICS codes for the 2000 Census and the ACS/PRCS from 2000-onward is available here:

INDNAICS Crosswalk]]></codInstr>
      <concept vocab="IPUMS">Work Variables -- PERSON</concept>
      <varFormat schema="other" type="character"/>
    </var>
    <var ID="INCWAGE" dcml="0" files="ExtractData" intrvl="contin" name="INCWAGE">
      <location EndPos="38" StartPos="33" width="6"/>
      <labl>Wage and salary income</labl>
      <txt><![CDATA[INCWAGE reports each respondent's total pre-tax wage and salary income - that is, money received as an employee - for the previous year. The censuses collected information on income received from these sources during the previous calendar year; for the ACS and the PRCS, the reference period was the past 12 months. Sources of income in INCWAGE include wages, salaries, commissions, cash bonuses, tips, and other money income received from an employer. Payments-in-kind or reimbursements for business expenses are not included. See the comparability discussion below for further information.

Amounts are expressed in contemporary dollars, and users studying change over time must adjust for inflation (See INCTOT for Consumer Price Index adjustment factors). The exception is the ACS/PRCS multi-year files, where all dollar amounts have been standardized to dollars as valued in the final year of data included in the file (e.g., 2007 dollars for the 2005-2007 3-year file). Additionally, more detail may be available than exists in the original ACS samples.

User Note: ACS respondents are surveyed throughout the year, and amounts do not reflect calendar year dollars. While the Census Bureau provides an adjustment factor (available in ADJUST), this is an imperfect solution. See the ACS income variables note for further details.]]></txt>
      <codInstr><![CDATA[CodesINCWAGE is a 7-digit numeric code reporting each respondent's total pre-tax wage and salary income - that is, money received as an employee - for the previous year. INCWAGE specific variable codes for missing, edited, or unidentified observations, observations not applicable (N/A), observations not in universe (NIU), top and bottom value coding, etc. are provided below by Census year (and data sample if specified).

User Note: Amounts are expressed in contemporary dollars, and users studying change over time must adjust for inflation (See Description).

INCWAGE Specific Variable Codes
999999 = N/A
999998 = Missing


* .indent {
  text-indent: 10px;
}


* .lrgindent {
  text-indent: 85px;
}



	
		INCWAGE
	
		Census
		Top Code
	
		1940
		$5,001
	
		1950
		$10,000
	
		1960
		$25,000
	
		1970
		$50,000
	
		1980
		$75,000
	
		1990
		&nbsp;$140,000*
	
		2000
		&nbsp;&nbsp;$175,000**
	
		ACS (2000-2002) 
		&nbsp;&nbsp;$200,000**
	
		ACS (2003-onward)
		&nbsp;99.5th Percentile in State**
	
		&nbsp;PRCS (2005-onward)
		&nbsp;99.5th Percentile in State**
	


]]></codInstr>
      <concept vocab="IPUMS">Income Variables -- PERSON</concept>
      <varFormat schema="other" type="numeric"/>
    </var>
  </dataDscr>
</codeBook>
